portalksp/__init__.py
portalksp/main.py
portalksp-0.1.dist-info/LICENSE
portalksp-0.1.dist-info/METADATA
portalksp-0.1.dist-info/WHEEL
portalksp-0.1.dist-info/entry_points.txt
portalksp-0.1.dist-info/top_level.txt
portalksp-0.1.dist-info/RECORD
