Metadata-Version: 2.1
Name: portalksp
Version: 0.1
Summary: A Portalksp package
Home-page: https://github.com/emhayusa/portalksp
Author: Muhammad Hasannudin Yusa
Author-email: emhayusa@gmail.com
License: UNKNOWN
Platform: UNKNOWN
Classifier: Programming Language :: Python :: 3
Classifier: License :: OSI Approved :: MIT License
Classifier: Operating System :: OS Independent
Requires-Dist: Click
